social_auth_gsis/backends.py
social_auth_gsis/pipeline/social_auth.py
social_auth_gsis-0.5.8.dist-info/METADATA
social_auth_gsis-0.5.8.dist-info/WHEEL
social_auth_gsis-0.5.8.dist-info/RECORD
