Metadata-Version: 2.1
Name: social-auth-gsis
Version: 0.5.8
Summary: Social Auth backend for GSIS
License: MIT
Author: Paris Kasidiaris
Author-email: paris@withlogic.co
Requires-Python: >=3.8
Classifier: License :: OSI Approved :: MIT License
Classifier: Programming Language :: Python :: 3
Classifier: Programming Language :: Python :: 3.8
Classifier: Programming Language :: Python :: 3.9
Classifier: Programming Language :: Python :: 3.10
Classifier: Programming Language :: Python :: 3.11
Classifier: Programming Language :: Python :: 3.12
Requires-Dist: django (>=4.2.0)
Requires-Dist: requests (>=2.31.0,<3.0.0)
Requires-Dist: social-auth-app-django (>=5.0.0,<6.0.0)
Requires-Dist: social-auth-core (>=4.5.2,<5.0.0)
Requires-Dist: xmltodict (>=0.13.0,<0.14.0)
